LICENSE
metarchive/__init__.py
metarchive/algebra/__init__.py
metarchive/algebra/acquisition.py
metarchive/algebra/analysis.py
metarchive/algebra/log.py
metarchive/algebra/storage.py
metarchive/algebra/types.py
metarchive/analysis/__init__.py
metarchive/analysis/engines/__init__.py
metarchive/analysis/engines/beautifulsoup.py
metarchive/aquicision/__init__.py
metarchive/aquicision/basic.py
metarchive/aquicision/progress.py
metarchive/interface/__init__.py
metarchive/interface/console/__init__.py
metarchive/interface/console/reconstruct.py
metarchive/interface/console.py
metarchive/interface/helper/__init__.py
metarchive/interface/helper/list_pages.py
metarchive/reconstruction/__init__.py
metarchive/reconstruction/links.py
metarchive/reconstruction/storage/__init__.py
metarchive/reconstruction/storage/basic.py
metarchive/reconstruction/storage/directory.py
metarchive-0.6.1.dist-info/LICENSE
metarchive-0.6.1.dist-info/WHEEL
metarchive-0.6.1.dist-info/METADATA
metarchive-0.6.1.dist-info/RECORD
