Metadata-Version: 2.1
Name: metarchive
Version: 0.6.1
Summary: Tool for analysing links within a website archived by archive.org
Home-page: https://gitlab.com/patrick.daniel.gress/osmium
License: GPLv3
Keywords: archive.org,analysis
Author: Patrick Greß
Author-email: patrick.daniel.gress@gmail.com
Requires-Python: >=3.10,<4.0
Classifier: Development Status :: 4 - Beta
Classifier: Intended Audience :: Science/Research
Classifier: License :: OSI Approved :: GNU General Public License v3 (GPLv3)
Classifier: License :: Other/Proprietary License
Classifier: Operating System :: OS Independent
Classifier: Programming Language :: Python :: 3
Classifier: Programming Language :: Python :: 3.10
Classifier: Topic :: Internet :: WWW/HTTP :: Indexing/Search
Classifier: Topic :: Text Processing :: Markup :: HTML
Requires-Dist: PyYAML (>=6.0,<7.0)
Requires-Dist: beautifulsoup4 (>=4.10.0,<5.0.0)
Requires-Dist: more-itertools (>=8.12.0,<9.0.0)
Requires-Dist: pydantic (>=1.9.0,<2.0.0)
Requires-Dist: python-magic (>=0.4.25,<0.5.0)
Requires-Dist: requests (>=2.27.1,<3.0.0)
Requires-Dist: toolz (>=0.11.2,<0.12.0)
Requires-Dist: tqdm (>=4.63.0,<5.0.0)
Project-URL: Documentation, https://metarchive.readthedocs.io/en/latest/
Project-URL: Repository, https://gitlab.com/patrick.daniel.gress/osmium
